LibScout/__init__.py
LibScout/ch.py
LibScout/config.py
LibScout/files.py
LibScout/hashtree.py
LibScout/cli/__init__.py
LibScout/cli/entry_points.py
LibScout/cli/main.py
LibScout/core/__init__.py
LibScout/core/matcher.py
LibScout/core/profiler.py
LibScout/core/robot.py
LibScout/pkg/__init__.py
LibScout/pkg/tree.py
LibScout/pkg/utils.py
LibScout/profile/__init__.py
LibScout/profile/base.py
LibScout/profile/caches.py
LibScout/profile/match.py
mastf_libscout-0.1.1a1.dist-info/LICENSE
mastf_libscout-0.1.1a1.dist-info/METADATA
mastf_libscout-0.1.1a1.dist-info/WHEEL
mastf_libscout-0.1.1a1.dist-info/entry_points.txt
mastf_libscout-0.1.1a1.dist-info/top_level.txt
mastf_libscout-0.1.1a1.dist-info/RECORD
